{"title":"APP单项认证","uid":"a9cc9e80be87d52a4207fb04988da523","slug":"APP单项认证","date":"2025-05-17T08:20:25.669Z","updated":"2025-05-17T08:23:39.497Z","comments":true,"path":"api/articles/APP单项认证.json","cover":"https://myhaoblog.oss-cn-beijing.aliyuncs.com/blog%20%E5%9B%BE%E7%89%87/f292f751-55cf-4688-892f-d71c816d8dbe.jpg","content":"<h1 id=\"APP单项认证\"><a href=\"#APP单项认证\" class=\"headerlink\" title=\"APP单项认证\"></a>APP单项认证</h1><h2 id=\"单项认证的绕过：\"><a href=\"#单项认证的绕过：\" class=\"headerlink\" title=\"单项认证的绕过：\"></a>单项认证的绕过：</h2><p>没有限制过滤的抓包问题：<br>1、抓不到-工具证书没配置好<br>2、抓不到-app走的不是http&#x2F;s<br>有限制过滤的抓包问题：<br>3、抓不到-反模拟器调试<br>4、抓不到-反代理VPN<br>5、抓不到-反证书检验<br>做移动安全测试时，设置好了代理，但抓不到数据包<br>反抓包Demo：<a href=\"https://github.com/AndroidAppSec/vuls\">https://github.com/AndroidAppSec/vuls</a><br>反调试Demo：<a href=\"https://github.com/lamster2018/EasyProtector\">https://github.com/lamster2018/EasyProtector</a> </p>\n<p>防护手段：<br>1、反模拟器：禁用模拟器进行调试访问 </p>\n<p>2、反证书检验：SSL证书绑定（单向校验和双向校验）<br>单项校验-客户端校验服务端的证书。<br>双向认证-客户端不仅仅要校验服务端的证书，<br>也会在app内放一张证书；服务端也会检验客户端里的证书。 </p>\n<p>3、反代理VPN：代理检测、VPN检测、发包框架强制不走代理<br>配置代理后无法访问，数据异常等<br>连接VPN节点后无法访问，数据异常等<br>配置代理后正常访问且无任何异常，但无数据包 </p>\n<p>绕过手段：<br>-反模拟器：（某社交相亲）<br>1、用真机<br>2、模拟器模拟真机<br>3、逆向删反代码重打包 </p>\n<p>-反证书检验：（某游戏营地）<br>1、单向-XP框架<br>2、双向<br>3、逆向删反代码重打包<br>XP框架安装：<br><a href=\"https://blog.csdn.net/weixin_49941977/article/details/121318015\">https://blog.csdn.net/weixin_49941977/article/details/121318015</a><br>-反代理：<br>1、使用电脑端的proxfiter代理</p>\n<p>以 MuMu Android12 为例：</p>\n<p>1，安装 mask 面具：</p>\n<p><a href=\"https://mumu.163.com/help/20240202/35044_1136675.html#a2\">https://mumu.163.com/help/20240202/35044_1136675.html#a2</a></p>\n<p>2，Lsposed</p>\n<p><a href=\"https://github.com/LSPosed/LSPosed/releases/tag/v1.9.2\">https://github.com/LSPosed/LSPosed/releases/tag/v1.9.2</a></p>\n<p>并安装两个插件</p>\n<p><a href=\"https://github.com/scopion/xposed-ssl-pinning\">https://github.com/scopion/xposed-ssl-pinning</a></p>\n<p><img src=\"https://myhaoblog.oss-cn-beijing.aliyuncs.com/blog%20%E5%9B%BE%E7%89%87/%E5%9B%BE%E7%89%87.png\"></p>\n","text":"APP单项认证单项认证的绕过：没有限制过滤的抓包问题：1、抓不到-工具证书没配置好2、抓不到-app走的不是http/s有限制过滤的抓包问题：3、抓不到-反模拟...","permalink":"/post/APP单项认证","photos":[],"count_time":{"symbolsCount":828,"symbolsTime":"1 mins."},"categories":[{"name":"基础知识","slug":"基础知识","count":12,"path":"api/categories/基础知识.json"}],"tags":[{"name":"基础","slug":"基础","count":12,"path":"api/tags/基础.json"}],"toc":"<ol class=\"toc\"><li class=\"toc-item toc-level-1\"><a class=\"toc-link\" href=\"#APP%E5%8D%95%E9%A1%B9%E8%AE%A4%E8%AF%81\"><span class=\"toc-text\">APP单项认证</span></a><ol class=\"toc-child\"><li class=\"toc-item toc-level-2\"><a class=\"toc-link\" href=\"#%E5%8D%95%E9%A1%B9%E8%AE%A4%E8%AF%81%E7%9A%84%E7%BB%95%E8%BF%87%EF%BC%9A\"><span class=\"toc-text\">单项认证的绕过：</span></a></li></ol></li></ol>","author":{"name":"Hao","slug":"blog-author","avatar":"https://myhaoblog.oss-cn-beijing.aliyuncs.com/ppp/64966b30e1c9375e8dbb11146ea9c12f.jpg","link":"/","description":"山高自有客行路，水深自有渡船认 The future is like the sea and three will be a long time to come","socials":{"github":"https://github.com/isMyHao","twitter":"","stackoverflow":"","wechat":"","qq":"","weibo":"","zhihu":"https://www.zhihu.com/","csdn":"https://blog.csdn.net/2401_87971103?spm=1000.2115.3001.10640","juejin":"","customs":{}}},"mapped":true,"hidden":false,"prev_post":{"title":"APP单项认证","uid":"a9cc9e80be87d52a4207fb04988da523","slug":"APP双向认证","date":"2025-05-17T08:23:14.760Z","updated":"2025-05-17T08:26:55.082Z","comments":true,"path":"api/articles/APP双向认证.json","cover":"https://myhaoblog.oss-cn-beijing.aliyuncs.com/blog%20%E5%9B%BE%E7%89%87/f42db79a-f567-48f7-a81f-3ea7804ed631.jpg","text":"APP单项认证常见的 Android 安全工具 移动安全框架 (MobSF) 是一种自动化的一体化移动应用程序(Android/iOS/Windows) 渗透测...","permalink":"/post/APP双向认证","photos":[],"count_time":{"symbolsCount":"1.8k","symbolsTime":"2 mins."},"categories":[{"name":"基础知识","slug":"基础知识","count":12,"path":"api/categories/基础知识.json"}],"tags":[{"name":"基础","slug":"基础","count":12,"path":"api/tags/基础.json"}],"author":{"name":"Hao","slug":"blog-author","avatar":"https://myhaoblog.oss-cn-beijing.aliyuncs.com/ppp/64966b30e1c9375e8dbb11146ea9c12f.jpg","link":"/","description":"山高自有客行路，水深自有渡船认 The future is like the sea and three will be a long time to come","socials":{"github":"https://github.com/isMyHao","twitter":"","stackoverflow":"","wechat":"","qq":"","weibo":"","zhihu":"https://www.zhihu.com/","csdn":"https://blog.csdn.net/2401_87971103?spm=1000.2115.3001.10640","juejin":"","customs":{}}}},"next_post":{"title":"PHP-反序列化","uid":"ac5ba92b195ea22428b99b3d70a46fa1","slug":"PHP-反序列化","date":"2025-05-17T08:10:22.090Z","updated":"2025-05-17T08:37:30.224Z","comments":true,"path":"api/articles/PHP-反序列化.json","cover":"https://myhaoblog.oss-cn-beijing.aliyuncs.com/blog%20%E5%9B%BE%E7%89%87/fcb0635d92f79ea826b197540ffc8cbc.jpg","text":"PHP-反序列化在 PHP 里，序列化是把一个对象或数组转换成字符串的过程（比如保存到文件或传输到网络），而反序列化就是把这个字符串还原成原来的变量（对象 / ...","permalink":"/post/PHP-反序列化","photos":[],"count_time":{"symbolsCount":"4.6k","symbolsTime":"4 mins."},"categories":[{"name":"PHP安全","slug":"PHP安全","count":1,"path":"api/categories/PHP安全.json"}],"tags":[{"name":"PHP安全","slug":"PHP安全","count":1,"path":"api/tags/PHP安全.json"}],"author":{"name":"Hao","slug":"blog-author","avatar":"https://myhaoblog.oss-cn-beijing.aliyuncs.com/ppp/64966b30e1c9375e8dbb11146ea9c12f.jpg","link":"/","description":"山高自有客行路，水深自有渡船认 The future is like the sea and three will be a long time to come","socials":{"github":"https://github.com/isMyHao","twitter":"","stackoverflow":"","wechat":"","qq":"","weibo":"","zhihu":"https://www.zhihu.com/","csdn":"https://blog.csdn.net/2401_87971103?spm=1000.2115.3001.10640","juejin":"","customs":{}}}}}